searchbible/README.md
searchbible/config.py
searchbible/health_check.py
searchbible/requirements.txt
searchbible/searchbible.py
searchbible/searchbibleconvertor.py
searchbible/convertor/bible.py
searchbible/data/NET.bible
searchbible/utils/AGBparagraphs_expanded.py
searchbible/utils/AGBsubheadings.py
searchbible/utils/BibleBooks.py
searchbible/utils/TextUtil.py
searchbible/utils/prompt_shared_key_bindings.py
searchbible/utils/streaming_word_wrapper.py
biblesearchai-0.0.12.dist-info/METADATA
biblesearchai-0.0.12.dist-info/WHEEL
biblesearchai-0.0.12.dist-info/entry_points.txt
biblesearchai-0.0.12.dist-info/top_level.txt
biblesearchai-0.0.12.dist-info/RECORD
