Metadata-Version: 2.1
Name: biblesearchai
Version: 0.0.12
Summary: Search Bible AI - Integrate Unique Bible App resources with AI tools
Home-page: https://letmedoit.ai
Author: Eliran Wong
Author-email: support@letmedoit.ai
License: GNU General Public License (GPL)
Project-URL: Source, https://github.com/eliranwong/searchbibleai
Project-URL: Tracker, https://github.com/eliranwong/searchbibleai/issues
Project-URL: Documentation, https://github.com/eliranwong/searchbibleai/wiki
Project-URL: Funding, https://www.paypal.me/MarvelBible
Keywords: ai unique bible search openai google chatgpt gemini chromadb
Classifier: Development Status :: 5 - Production/Stable
Classifier: Intended Audience :: End Users/Desktop
Classifier: Topic :: Utilities
Classifier: License :: OSI Approved :: GNU General Public License v3 or later (GPLv3+)
Classifier: Programming Language :: Python :: 3.8
Classifier: Programming Language :: Python :: 3.9
Classifier: Programming Language :: Python :: 3.10
Classifier: Programming Language :: Python :: 3.11
Classifier: Programming Language :: Python :: 3.12
Requires-Python: >=3.8
Requires-Dist: prompt-toolkit
Requires-Dist: pygments
Requires-Dist: pyperclip
Requires-Dist: openai ==1.3.5
Requires-Dist: google-cloud-aiplatform
Requires-Dist: apsw
Requires-Dist: sentence-transformers
Requires-Dist: chromadb
